LICENSE
MANIFEST.in
setup.py
Flask_Auth.egg-info/PKG-INFO
Flask_Auth.egg-info/SOURCES.txt
Flask_Auth.egg-info/dependency_links.txt
Flask_Auth.egg-info/namespace_packages.txt
Flask_Auth.egg-info/not-zip-safe
Flask_Auth.egg-info/requires.txt
Flask_Auth.egg-info/top_level.txt
docs/Makefile
docs/api.rst
docs/conf.py
docs/index.rst
docs/quickstart.rst
docs/_themes/.gitignore
docs/_themes/LICENSE
docs/_themes/README
docs/_themes/flask_theme_support.py
docs/_themes/flask_theme_support.pyc
docs/_themes/.git/HEAD
docs/_themes/.git/config
docs/_themes/.git/description
docs/_themes/.git/index
docs/_themes/.git/packed-refs
docs/_themes/.git/hooks/applypatch-msg.sample
docs/_themes/.git/hooks/commit-msg.sample
docs/_themes/.git/hooks/post-commit.sample
docs/_themes/.git/hooks/post-receive.sample
docs/_themes/.git/hooks/post-update.sample
docs/_themes/.git/hooks/pre-applypatch.sample
docs/_themes/.git/hooks/pre-commit.sample
docs/_themes/.git/hooks/pre-rebase.sample
docs/_themes/.git/hooks/prepare-commit-msg.sample
docs/_themes/.git/hooks/update.sample
docs/_themes/.git/info/exclude
docs/_themes/.git/logs/HEAD
docs/_themes/.git/logs/refs/heads/master
docs/_themes/.git/objects/pack/pack-c59acb6dab44178f3f0ceda2c240adbf9c0af295.idx
docs/_themes/.git/objects/pack/pack-c59acb6dab44178f3f0ceda2c240adbf9c0af295.pack
docs/_themes/.git/refs/heads/master
docs/_themes/.git/refs/remotes/origin/HEAD
docs/_themes/flask/layout.html
docs/_themes/flask/relations.html
docs/_themes/flask/theme.conf
docs/_themes/flask/static/flasky.css_t
docs/_themes/flask/static/small_flask.css
docs/_themes/flask_small/layout.html
docs/_themes/flask_small/theme.conf
docs/_themes/flask_small/static/flasky.css_t
examples/no_db_persistence.py
examples/permissions.py
examples/sqlalchemy_model.py
examples/.ropeproject/config.py
flaskext/__init__.py
flaskext/auth/__init__.py
flaskext/auth/auth.py
flaskext/auth/permissions.py
flaskext/auth/models/__init__.py
flaskext/auth/models/sa.py