Metadata-Version: 1.0
Name: Flask-Auth
Version: 0.8
Summary: Auth extension for Flask.
Home-page: http://bitbucket.org/Shotca/flask-auth/
Author: Lars de Ridder
Author-email: shotcage@gmail.com
License: BSD
Platform: any
Classifier: Development Status :: 4 - Beta
Classifier: Environment :: Web Environment
Classifier: Intended Audience :: Developers
Classifier: License :: OSI Approved :: BSD License
Classifier: Operating System :: OS Independent
Classifier: Programming Language :: Python
Classifier: Topic :: Internet :: WWW/HTTP :: Dynamic Content
Classifier: Topic :: Software Development :: Libraries :: Python Modules
